MANIFEST.in
README.md
setup.py
bin/__init__.py
bin/ddp_getpar.cmd
bin/ddp_getpar.py
bin/ddp_pvtr.cmd
bin/ddp_pvtr.py
bin/ddp_spec.cmd
bin/ddp_spec.py
ddp/__init__.py
ddp/getpar.py
ddp/inc.py
ddp/pvtr.py
ddp/spec.py
ddp.egg-info/PKG-INFO
ddp.egg-info/SOURCES.txt
ddp.egg-info/dependency_links.txt
ddp.egg-info/requires.txt
ddp.egg-info/top_level.txt
ddp/Template/ddpostprocess.tpl
ddp/Template/ddscat.tpl
ddp/Template/ddscat_builtin.tpl