Metadata-Version: 1.0
Name: ddp
Version: 0.16
Summary: This is a package can be used to process vtr files.
Home-page: https://github.com/xingtingyang/ddp
Author: Xing
Author-email: 1281961491@qq.com
License: BSD style
Platform: UNKNOWN
